agentvault/__init__.py
agentvault/agent_card_utils.py
agentvault/client.py
agentvault/exceptions.py
agentvault/key_manager.py
agentvault/mcp_utils.py
agentvault/models/__init__.py
agentvault/models/a2a_protocol.py
agentvault/models/agent_card.py
agentvault/protocols/__init__.py
agentvault-0.2.1.dist-info/LICENSE
agentvault-0.2.1.dist-info/METADATA
agentvault-0.2.1.dist-info/WHEEL
agentvault-0.2.1.dist-info/RECORD
