Metadata-Version: 2.3
Name: agentvault
Version: 0.2.1
Summary: Core Python client library for A2A protocol, MCP, and secure local key management.
License: Apache-2.0
Keywords: ai,agent,a2a,mcp,security,api,llm,interoperability,key-management,python,library,client,sdk
Author: Raphael Zbigniew Jeziorny
Author-email: AgentVault@proton.me
Requires-Python: >=3.10,<3.12
Classifier: Development Status :: 3 - Alpha
Classifier: Intended Audience :: Developers
Classifier: License :: OSI Approved :: Apache Software License
Classifier: Operating System :: OS Independent
Classifier: Programming Language :: Python :: 3
Classifier: Programming Language :: Python :: 3.10
Classifier: Programming Language :: Python :: 3.11
Classifier: Topic :: Security
Classifier: Topic :: Software Development :: Libraries :: Python Modules
Classifier: Topic :: Communications
Classifier: Topic :: Scientific/Engineering :: Artificial Intelligence
Classifier: Typing :: Typed
Provides-Extra: dev
Provides-Extra: os-keyring
Requires-Dist: agentvault-testing-utils ; extra == "dev"
Requires-Dist: httpx[brotli,http2] (>=0.27,<0.28)
Requires-Dist: keyring (>=24,<25) ; extra == "os-keyring"
Requires-Dist: pydantic (>=2.0,<3.0)
Requires-Dist: pytest (>=7.0,<9.0) ; extra == "dev"
Requires-Dist: pytest-asyncio (>=0.23,<0.24) ; extra == "dev"
Requires-Dist: pytest-mock (>=3.12,<4.0) ; extra == "dev"
Requires-Dist: python-dotenv (>=1.0,<2.0)
Requires-Dist: respx (>=0.20,<0.21) ; extra == "dev"
